gitinclude/__init__.py
gitinclude/_version.py
gitinclude-0.3.1.dist-info/LICENSE
gitinclude-0.3.1.dist-info/METADATA
gitinclude-0.3.1.dist-info/WHEEL
gitinclude-0.3.1.dist-info/top_level.txt
gitinclude-0.3.1.dist-info/RECORD
