Metadata-Version: 2.1
Name: gitinclude
Version: 0.3.1
Summary: literalinclude from git repository.
Home-page: https://github.com/ousttrue/sphinxcontrib-git_include
Author: ousttrue
Author-email: ousttrue@gmail.com
Maintainer: ousttrue
License: Apache-2.0
Keywords: sphinx,sphinxcontrib
Platform: any
Classifier: Development Status :: 4 - Beta
Classifier: Framework :: Sphinx :: Extension
Classifier: Intended Audience :: Developers
Classifier: License :: OSI Approved :: MIT License
Classifier: Operating System :: OS Independent
Classifier: Programming Language :: Python :: 3
Classifier: Topic :: Documentation :: Sphinx
License-File: LICENSE
Requires-Dist: Sphinx
